dotted/__init__.py
dotted/api.py
dotted/elements.py
dotted/grammar.py
dotted/transforms.py
tests/__init__.py
tests/test_api.py
tests/test_appender.py
tests/test_assemble.py
tests/test_attrs.py
tests/test_filter_keyvalue.py
tests/test_get.py
tests/test_invert.py
tests/test_match.py
tests/test_negation.py
tests/test_numeric.py
tests/test_pluck.py
tests/test_slice.py
tests/test_transforms.py
tests/test_update.py
dotted_notation-0.18.2.dist-info/LICENSE
dotted_notation-0.18.2.dist-info/METADATA
dotted_notation-0.18.2.dist-info/WHEEL
dotted_notation-0.18.2.dist-info/top_level.txt
dotted_notation-0.18.2.dist-info/RECORD
