Metadata-Version: 2.1
Name: dotted-notation
Version: 0.18.2
Summary: Dotted notation for safe nested data traversal with optional chaining, pattern matching, and transforms
Home-page: https://github.com/freywaid/dotted
Author: Frey Waid
Author-email: logophage1@gmail.com
License: MIT license
Classifier: Development Status :: 3 - Alpha
Classifier: Programming Language :: Python :: 3
Classifier: License :: OSI Approved :: MIT License
Classifier: Operating System :: OS Independent
Requires-Python: >=3.6
License-File: LICENSE
Requires-Dist: pyparsing >=3.0
